README.rst
setup.py
fabric_docker/__init__.py
fabric_docker/fabric_docker.py
fabric_docker/parse.py
fabric_docker/util.py
fabric_docker.egg-info/PKG-INFO
fabric_docker.egg-info/SOURCES.txt
fabric_docker.egg-info/dependency_links.txt
fabric_docker.egg-info/requires.txt
fabric_docker.egg-info/top_level.txt