Metadata-Version: 1.1
Name: fabric-docker
Version: 0.1
Summary: Docker command-line tool wrapper for Fabric.
Home-page: https://github.com/malexer/fabric-docker
Author: Alex (Oleksii) Markov
Author-email: alex@markovs.me
License: MIT
Keywords: fabric fabfile docker docker-engine
Platform: UNKNOWN
Classifier: Development Status :: 3 - Alpha
Classifier: Intended Audience :: Developers
Classifier: Intended Audience :: System Administrators
Classifier: Topic :: Software Development :: Build Tools
Classifier: Topic :: Software Development :: Libraries :: Python Modules
Classifier: Topic :: System :: Clustering
Classifier: Topic :: System :: Software Distribution
Classifier: Topic :: System :: Systems Administration
Classifier: License :: OSI Approved :: MIT License
Classifier: Programming Language :: Python :: 2
Classifier: Programming Language :: Python :: 2.6
Classifier: Programming Language :: Python :: 2.7
